pdf_generator/__init__.py
pdf_generator/generator.py
pdf_generator/slides_generator.py
pdf_generator/utils.py
pdf_generator/preprocessor/__init__.py
pdf_generator/preprocessor/parsers/__init__.py
pdf_generator/preprocessor/parsers/health_history.py
pdf_generator/preprocessor/parsers/measurements.py
pdf_generator/preprocessor/parsers/patient_data.py
pdf_generator/preprocessor/parsers/triage.py
pdf_generator/styles/__init__.py
pdf_generator/styles/font/Roboto-Black.ttf
pdf_generator/styles/font/Roboto-BlackItalic.ttf
pdf_generator/styles/font/Roboto-Bold.ttf
pdf_generator/styles/font/Roboto-BoldItalic.ttf
pdf_generator/styles/font/Roboto-Italic.ttf
pdf_generator/styles/font/Roboto-Light.ttf
pdf_generator/styles/font/Roboto-LightItalic.ttf
pdf_generator/styles/font/Roboto-Medium.ttf
pdf_generator/styles/font/Roboto-MediumItalic.ttf
pdf_generator/styles/font/Roboto-Regular.ttf
pdf_generator/styles/font/Roboto-Thin.ttf
pdf_generator/styles/font/Roboto-ThinItalic.ttf
pdf_generator/styles/font/RobotoCondensed-Bold.ttf
pdf_generator/styles/font/RobotoCondensed-BoldItalic.ttf
pdf_generator/styles/font/RobotoCondensed-Italic.ttf
pdf_generator/styles/font/RobotoCondensed-Light.ttf
pdf_generator/styles/font/RobotoCondensed-LightItalic.ttf
pdf_generator/styles/font/RobotoCondensed-Regular.ttf
pdf_generator/styles/img/empty.png
pdf_generator/styles/img/logo.png
pdf_generator_advinow-0.4.2.dist-info/LICENCE
pdf_generator_advinow-0.4.2.dist-info/METADATA
pdf_generator_advinow-0.4.2.dist-info/WHEEL
pdf_generator_advinow-0.4.2.dist-info/top_level.txt
pdf_generator_advinow-0.4.2.dist-info/RECORD
