Metadata-Version: 2.1
Name: pdf-generator-advinow
Version: 0.4.2
Summary: Utility for producing PDFs from Doctor Notes.
Home-page: https://gitlab.com/AdviNow/pdf_generator/
Download-URL: https://gitlab.com/AdviNow/pdf_generator/-/archive/master/pdf_generator-master.tar.gz
Author: AdviNow Medical
License: MIT
Platform: UNKNOWN
License-File: LICENCE
Requires-Dist: neo4jrestclient
Requires-Dist: pandas
Requires-Dist: python-dotenv
Requires-Dist: reportlab
Requires-Dist: requests
Requires-Dist: restricted-pkg
Requires-Dist: python-dateutil
